{
  "GNTE6wLZuqT7LLXhn33LUNNNNFqL6FFcq8LxYgMKcobu": {
    "totalWagered": 0.6300000000000001,
    "gameHistory": [
      {
        "wageredAmount": 0.01,
        "netProfit": 0.01,
        "multiplier": 2,
        "gameMode": "1v1",
        "serverSeed": "962cdd9ca753bae6d4bff412b978116a",
        "clientSeed": "o0yts0nbof",
        "nonce": 18,
        "id": "game_1756468206183",
        "timestamp": "2025-08-29T11:50:06.183Z"
      },
      {
        "wageredAmount": 0.01,
        "netProfit": -0.01,
        "multiplier": 0,
        "gameMode": "1v1",
        "serverSeed": "7d733e17a075e93c7696b29d4ac3cf47",
        "clientSeed": "o0yts0nbof",
        "nonce": 17,
        "id": "game_1756468185732",
        "timestamp": "2025-08-29T11:49:45.732Z"
      },
      {
        "wageredAmount": 0.01,
        "netProfit": 0.01,
        "multiplier": 2,
        "gameMode": "1v1",
        "serverSeed": "",
        "clientSeed": "",
        "nonce": 0,
        "id": "game_1756468015621",
        "timestamp": "2025-08-29T11:46:55.621Z"
      },
      {
        "wageredAmount": 0.01,
        "netProfit": -0.01,
        "multiplier": 0,
        "gameMode": "1v1",
        "serverSeed": "7f3b6d830cac1649e21b77e186dd1c8e",
        "clientSeed": "o0yts0nbof",
        "nonce": 15,
        "id": "game_1756467721302",
        "timestamp": "2025-08-29T11:42:01.302Z"
      },
      {
        "wageredAmount": 0.01,
        "netProfit": 0.01,
        "multiplier": 2,
        "gameMode": "1v1",
        "serverSeed": "",
        "clientSeed": "",
        "nonce": 0,
        "id": "game_1756467567142",
        "timestamp": "2025-08-29T11:39:27.142Z"
      },
      {
        "wageredAmount": 0.01,
        "netProfit": -0.01,
        "multiplier": 0,
        "gameMode": "1v1",
        "serverSeed": "aa3984931a8fa91141685d581cbcae86",
        "clientSeed": "o0yts0nbof",
        "nonce": 13,
        "id": "game_1756467491013",
        "timestamp": "2025-08-29T11:38:11.013Z"
      },
      {
        "wageredAmount": 0.01,
        "netProfit": -0.01,
        "multiplier": 0,
        "gameMode": "1v1",
        "serverSeed": "",
        "clientSeed": "",
        "nonce": 0,
        "id": "game_1756467477647",
        "timestamp": "2025-08-29T11:37:57.647Z"
      },
      {
        "wageredAmount": 0.01,
        "netProfit": -0.01,
        "multiplier": 0,
        "gameMode": "1v1",
        "serverSeed": "63a9f7be9a5dfc6ed509ab65cc64b410",
        "clientSeed": "o0yts0nbof",
        "nonce": 11,
        "id": "game_1756467454695",
        "timestamp": "2025-08-29T11:37:34.695Z"
      },
      {
        "wageredAmount": 0.01,
        "netProfit": -0.01,
        "multiplier": 0,
        "gameMode": "1v1",
        "serverSeed": "",
        "clientSeed": "",
        "nonce": 0,
        "id": "game_1756467290843",
        "timestamp": "2025-08-29T11:34:50.843Z"
      },
      {
        "netProfit": 0.02374999999999998,
        "wageredAmount": 0.1,
        "multiplier": 1.2374999999999998,
        "gameMode": "solo",
        "serverSeed": "65d940b896813232ec9b57564e9c72a3",
        "clientSeed": "o0yts0nbof",
        "nonce": 125,
        "id": "game_1756467214423",
        "timestamp": "2025-08-29T11:33:34.423Z"
      },
      {
        "netProfit": -0.1,
        "wageredAmount": 0.1,
        "multiplier": 0,
        "gameMode": "solo",
        "serverSeed": "",
        "clientSeed": "o0yts0nbof",
        "nonce": 8,
        "id": "game_1756467201418",
        "timestamp": "2025-08-29T11:33:21.418Z"
      },
      {
        "wageredAmount": 0.01,
        "netProfit": -0.01,
        "multiplier": 0,
        "gameMode": "1v1",
        "serverSeed": "",
        "clientSeed": "",
        "nonce": 0,
        "id": "game_1756467016780",
        "timestamp": "2025-08-29T11:30:16.780Z"
      },
      {
        "netProfit": -0.1,
        "wageredAmount": 0.1,
        "multiplier": 0,
        "gameMode": "solo",
        "serverSeed": "198fe7d5fbd98b8499871b6e7b6c0971",
        "clientSeed": "o0yts0nbof",
        "nonce": 103,
        "id": "game_1756466464662",
        "timestamp": "2025-08-29T11:21:04.662Z"
      },
      {
        "wageredAmount": 0.01,
        "netProfit": -0.01,
        "multiplier": 0,
        "gameMode": "1v1",
        "serverSeed": "8d8419d23263898d23ed0e7c57ca3401",
        "clientSeed": "o0yts0nbof",
        "nonce": 5,
        "id": "game_1756466127032",
        "timestamp": "2025-08-29T11:15:27.032Z"
      },
      {
        "wageredAmount": 0.01,
        "netProfit": -0.01,
        "multiplier": 0,
        "gameMode": "1v1",
        "serverSeed": "545d194fa95860576fa9232a32625ede",
        "clientSeed": "o0yts0nbof",
        "nonce": 4,
        "id": "game_1756466082424",
        "timestamp": "2025-08-29T11:14:42.424Z"
      },
      {
        "wageredAmount": 0.1,
        "netProfit": -0.1,
        "multiplier": 0,
        "gameMode": "1v1",
        "serverSeed": "",
        "clientSeed": "",
        "nonce": 0,
        "id": "game_1756465848629",
        "timestamp": "2025-08-29T11:10:48.629Z"
      },
      {
        "wageredAmount": 0.1,
        "netProfit": -0.1,
        "multiplier": 0,
        "gameMode": "1v1",
        "serverSeed": "",
        "clientSeed": "",
        "nonce": 0,
        "id": "game_1756465842404",
        "timestamp": "2025-08-29T11:10:42.404Z"
      },
      {
        "wageredAmount": 0.01,
        "netProfit": 0.01,
        "multiplier": 2,
        "gameMode": "1v1",
        "serverSeed": "84af0e5bf0fc8bf7c8d78847c8dcc682",
        "clientSeed": "o0yts0nbof",
        "nonce": 1,
        "id": "game_1756465599198",
        "timestamp": "2025-08-29T11:06:39.198Z"
      }
    ]
  }
}